CHANGES.rst
DESCRIPTION.rst
LICENSE
MANIFEST.in
README.md
setup.py
src/pic/__init__.py
src/pic/export.py
src/pic/info.py
src/pic/main.py
src/pic/poll.py
src/pic/predict.py
src/pic/predict_redis.py
src/pic/utils.py
src/wai.pytorchimageclass.egg-info/PKG-INFO
src/wai.pytorchimageclass.egg-info/SOURCES.txt
src/wai.pytorchimageclass.egg-info/dependency_links.txt
src/wai.pytorchimageclass.egg-info/entry_points.txt
src/wai.pytorchimageclass.egg-info/requires.txt
src/wai.pytorchimageclass.egg-info/top_level.txt