Metadata-Version: 2.1
Name: wai.pytorchimageclass
Version: 0.0.2
Summary: Command-line tools for building and applying PyTorch image classification models.
Home-page: https://github.com/waikato-datamining/pytorch/image-classification
Author: Peter Reutemann
Author-email: fracpete@waikato.ac.nz
License: BSD-3-Clause License
Platform: UNKNOWN
Classifier: Development Status :: 4 - Beta
Classifier: License :: OSI Approved :: BSD License
Classifier: Topic :: Scientific/Engineering :: Artificial Intelligence
Classifier: Programming Language :: Python :: 3
License-File: LICENSE
